README.md
setup.py
pulumi_openai/__init__.py
pulumi_openai/_inputs.py
pulumi_openai/_utilities.py
pulumi_openai/assistant.py
pulumi_openai/file.py
pulumi_openai/finetuning_job.py
pulumi_openai/get_file.py
pulumi_openai/get_files.py
pulumi_openai/get_finetuning_job.py
pulumi_openai/get_finetuning_jobs.py
pulumi_openai/get_model.py
pulumi_openai/get_models.py
pulumi_openai/outputs.py
pulumi_openai/provider.py
pulumi_openai/pulumi-plugin.json
pulumi_openai/py.typed
pulumi_openai.egg-info/PKG-INFO
pulumi_openai.egg-info/SOURCES.txt
pulumi_openai.egg-info/dependency_links.txt
pulumi_openai.egg-info/not-zip-safe
pulumi_openai.egg-info/requires.txt
pulumi_openai.egg-info/top_level.txt
pulumi_openai/config/__init__.py
pulumi_openai/config/__init__.pyi
pulumi_openai/config/vars.py